aid_deploy/__init__.py
aid_deploy/builder.py
aid_deploy/cli.py
aid_deploy/instance.py
aid_deploy/scanner.py
aid_deploy-0.1.dist-info/METADATA
aid_deploy-0.1.dist-info/WHEEL
aid_deploy-0.1.dist-info/entry_points.txt
aid_deploy-0.1.dist-info/RECORD
