Metadata-Version: 2.4
Name: aid-deploy
Version: 0.1
Summary: Docker compose command builder/executor
Classifier: License :: OSI Approved :: MIT License
Classifier: Operating System :: OS Independent
Classifier: Programming Language :: Python :: 3
Requires-Python: >=3.10
